.coveragerc
.travis.yml
Pipfile
Pipfile.lock
README.md
__init__.py
bandit.yml
codecov.yml
logging.ini
setup.py
test.py
gmrs/ config.ini
gmrs/__init__.py
gmrs/graph/__init__.py
gmrs/graph/edge.py
gmrs/graph/node.py
gmrs/model/__init__.py
gmrs/model/capability.py
gmrs/model/goal.py
gmrs/model/mission.py
gmrs/model/operator.py
gmrs/model/property.py
gmrs/model/scenario.py
gmrs/model/task.py
gmrs/model/unit.py
gmrs/objective/__init__.py
gmrs/objective/objective.py
gmrs/objective/probability.py
gmrs/objective/property_base.py
gmrs/objective/time.py
gmrs/objective/utils.py
gmrs/planner/__init__.py
gmrs/planner/build_variability_model.py
gmrs/planner/context.py
gmrs/planner/estimator.py
gmrs/planner/evaluation.py
gmrs/planner/functions.py
gmrs/planner/manager.py
gmrs/planner/outcome.py
gmrs/planner/pareto_front_reducer.py
gmrs/planner/skill_base.py
gmrs/planner/submodel.py
gmrs/planner/task_context.py
gmrs/planner/utils.py
gmrs/planner/container/__init__.py
gmrs/planner/container/containers.py
gmrs/planner/operators/__init__.py
gmrs/planner/operators/ievaluator.py
gmrs/planner/operators/operator.py
gmrs/planner/operators/sequential.py
gmrs/planner/unwind/base_operators.py
gmrs/service/base.py
gmrs/services/base.py
gmrs/services/skills_repository.py
gmrs/skill/skill_base.py
gmrs/util/__init__.py
gmrs/util/factory.py
gmrs/util/mission_specification.py
gmrs/util/model.py
gmrs/util/physics.py
gmrs/util/planning.py
gmrs/world/location.py
gmrs/world/map_of_distance.py
gmrs/world/scenario.py
gmrs/world/world_map.py
gmrs/world/world_model.py
hmrsplanner.egg-info/PKG-INFO
hmrsplanner.egg-info/SOURCES.txt
hmrsplanner.egg-info/dependency_links.txt
hmrsplanner.egg-info/top_level.txt
tests/__init__.py
tests/planner/__init__.py
tests/planner/test_multiple_configurations.py
tests/planner/test_pareto_front_reducer.py
tests/planner/test_scalability.py
tests/planner/test_sequential.py
tests/planner/test_utils.py
tests/planner/utils.py
tests/scenario/__init__.py
tests/scenario/fixture/__init__.py
tests/scenario/fixture/minimal_hospital_world_clean_room.py
tests/scenario/minimal_world/move_capability.py
