Metadata-Version: 2.1
Name: hmrsplanner
Version: 0.0.7
Summary: Planner for Heterogeneous Multi-Robots Systems
Home-page: https://github.com/gabrielsr/hmrsplanner
Author: Gabriel Rodrigues
Author-email: gabrielsr@gmail.com
License: UNKNOWN
Platform: UNKNOWN
Classifier: Programming Language :: Python :: 3
Classifier: License :: OSI Approved :: MIT License
Classifier: Operating System :: OS Independent
Requires-Python: >=3.8
